resumeassistant/__init__.py
resumeassistant/data/__init__.py
resumeassistant/data/candidate_record.py
resumeassistant/operator/__init__.py
resumeassistant/operator/worker.py
resumeassistant-0.1.0.dist-info/LICENSE
resumeassistant-0.1.0.dist-info/METADATA
resumeassistant-0.1.0.dist-info/WHEEL
resumeassistant-0.1.0.dist-info/top_level.txt
resumeassistant-0.1.0.dist-info/RECORD
