Metadata-Version: 2.1
Name: resumeassistant
Version: 0.1.0
Summary: Resume Assistant
Home-page: https://github.com/harish2sista/resumeassistant.git
Author: Harish Sita
Author-email: harish2sista@gmail.com
License: BSD 3-Clause License
Project-URL: Bug Tracker, https://github.com/harish2sista/resumeassistant.git
License-File: LICENSE
Requires-Dist: openai
Requires-Dist: pdf2image
Requires-Dist: poppler
